lobio/SeqIOUtils.py
lobio/SeqUtils.py
lobio/__init__.py
lobio/__version__.py
lobio/exceptions.py
lobio/models.py
lobio/region.py
lobio/span.py
lobio-0.5.6.dist-info/WHEEL
lobio-0.5.6.dist-info/METADATA
lobio-0.5.6.dist-info/RECORD
