Metadata-Version: 2.1
Name: lobio
Version: 0.5.6
Summary: Extra utilities for BioPython
Home-page: https://www.github.com/jvrana/LoBio
Author: Justin Vrana
Author-email: justin.vrana@gmail.com
Requires-Python: >=3.5,<4.0
Classifier: Programming Language :: Python :: 3
Classifier: Programming Language :: Python :: 3.5
Classifier: Programming Language :: Python :: 3.6
Classifier: Programming Language :: Python :: 3.7
Requires-Dist: biopython (>=1.73,<2.0)
Project-URL: Documentation, https://www.github.com/jvrana/LoBio
Project-URL: Repository, https://www.github.com/jvrana/LoBio
